{
	"group": "ПИз1821",
	"number": "3-23-01-18",
	"type": "Курсовая",
	"subtype": "Основная",
	"state": "Открыта",
	"unit": 5,
	"hours": 180,
	"doc": "document.pdf",
	"startDate": "4 апреля 2022 г.",
	"closeDate": "12 апреля 2022 г.",
	"deadline": "7 апреля 2022 г.",
	"examDate": "4 апреля 2022 г.",
	"eventDate": "4 апреля 2022 г.",
	"eventTime": "10:00",
	"students": [
		{
			"name": "Алаева Эмилия Игоревна",
			"value": "Зачёт"
		},
		{
			"name": "Безуглый Илья Андреевич",
			"value": "Незачёт"
		},
		{
			"name": "Броваров Олег Евгеньевич",
			"value": "Зачёт"
		},
		{
			"name": "Волков Семён Романович",
			"value": "Неявка"
		},
		{
			"name": "Ганжа Артём Александрович",
			"value": "Зачёт"
		},
		{
			"name": "Жданов Дмитрий Олегович",
			"value": "Зачёт"
		},
		{
			"name": "Клименко Татьяна Викторовна",
			"value": "Незачёт"
		},
		{
			"name": "Коринец Никита Валерьевич",
			"value": "Зачёт"
		},
		{
			"name": "Крисковец Мария Геннадьевна",
			"value": "Незачёт"
		},
		{
			"name": "Латрыгин Никита Евгеньевич",
			"value": "Зачёт"
		},
		{
			"name": "Меликов Ислам Аферович",
			"value": "Неявка"
		},
		{
			"name": "Панеш Роман Оскарович",
			"value": "Зачёт"
		},
		{
			"name": "Поляруш Артём Павлович",
			"value": "Зачёт"
		},
		{
			"name": "Прокофьев Павел Михайлович",
			"value": "Зачёт"
		}
	]
}
