{
	"requests": [
		{
			"sessionStopRequestId": 1,
			"facultyName": "Архитектурно-строительный",
			"courseName": "1 курс, 08.03.01 Строительство, \"Проектирование зданий\"  - Очная ф.о.",
			"requestDate": "05.09.2024 13:48",
			"shortText": "Нужно кое-что уточнить",
			"fullText": "Нужно кое-что уточнить относительно очень длиннных комментариев, которые могут не вместится в одну строку, и составлять треть 2-го тома «Войны и мира»",
			"approved": null,
			"approvalDate": null,
			"approvedByUmu": null,
			"approvedByDispatcher": null,
			"umuRelatedChanges": true,
			"dispatcherRelatedChanges": false,
			"sessionId": 4408
		}
	],
	"errors": null,
	"success": true
}
